aiohttp_jsonrpc/__init__.py
aiohttp_jsonrpc/client.py
aiohttp_jsonrpc/common.py
aiohttp_jsonrpc/exceptions.py
aiohttp_jsonrpc/handler.py
aiohttp_jsonrpc/py.typed
aiohttp_jsonrpc-0.4.0.dist-info/LICENSE
aiohttp_jsonrpc-0.4.0.dist-info/METADATA
aiohttp_jsonrpc-0.4.0.dist-info/WHEEL
aiohttp_jsonrpc-0.4.0.dist-info/top_level.txt
aiohttp_jsonrpc-0.4.0.dist-info/RECORD
