Metadata-Version: 2.1
Name: aiohttp-jsonrpc
Version: 0.4.0
Summary: aiohttp JSON-RPC server handler and client
Home-page: UNKNOWN
Author: Dmitry Orlov <me@mosquito.su>
License: MIT
Platform: all
Classifier: Environment :: Console
Classifier: Programming Language :: Python :: 3
Classifier: Programming Language :: Python :: 3 :: Only
Classifier: Programming Language :: Python :: 3.7
Classifier: Programming Language :: Python :: 3.8
Classifier: Programming Language :: Python :: 3.9
Classifier: Programming Language :: Python :: 3.10
License-File: LICENSE
Requires-Dist: aiohttp
Requires-Dist: typing-extensions ; python_version < "3.8"
Provides-Extra: develop
Requires-Dist: pytest ; extra == 'develop'
Requires-Dist: pytest-cov ; extra == 'develop'
Requires-Dist: pytest-aiohttp ; extra == 'develop'
